labm8/__init__.py
labm8/cache.py
labm8/crypto.py
labm8/db.py
labm8/fmt.py
labm8/fs.py
labm8/io.py
labm8/latex.py
labm8/make.py
labm8/math.py
labm8/modules.py
labm8/prof.py
labm8/system.py
labm8/text.py
labm8/time.py
labm8/viz.py
labm8-0.0.2.dist-info/DESCRIPTION.rst
labm8-0.0.2.dist-info/METADATA
labm8-0.0.2.dist-info/RECORD
labm8-0.0.2.dist-info/WHEEL
labm8-0.0.2.dist-info/metadata.json
labm8-0.0.2.dist-info/top_level.txt
labm8-0.0.2.dist-info/zip-safe
