Metadata-Version: 2.0
Name: labm8
Version: 0.0.2
Summary: Utils for manipulating quantitative experimental data
Home-page: https://github.com/ChrisCummins/labm8
Author: Chris Cummins
Author-email: chrisc.101@gmail.com
License: GNU General Public License, Version 3
Platform: UNKNOWN
Requires-Dist: humanize
Requires-Dist: numpy
Requires-Dist: pandas
Requires-Dist: scipy
